metaknowledge/RCglimpse.py
metaknowledge/__init__.py
metaknowledge/citation.py
metaknowledge/constants.py
metaknowledge/diffusion.py
metaknowledge/fileHandlers.py
metaknowledge/grantCollection.py
metaknowledge/graphHelpers.py
metaknowledge/mkCollection.py
metaknowledge/mkExceptions.py
metaknowledge/mkRecord.py
metaknowledge/progressBar.py
metaknowledge/recordCollection.py
metaknowledge/WOS/__init__.py
metaknowledge/WOS/recordWOS.py
metaknowledge/WOS/wosHandlers.py
metaknowledge/WOS/tagProcessing/__init__.py
metaknowledge/WOS/tagProcessing/funcDicts.py
metaknowledge/WOS/tagProcessing/helpFuncs.py
metaknowledge/WOS/tagProcessing/tagFunctions.py
metaknowledge/bin/__init__.py
metaknowledge/bin/metaknowledgeCLI.py
metaknowledge/bin/metaknowledgeDocsGen.py
metaknowledge/bin/metaknowledgeMdToNb.py
metaknowledge/contour/__init__.py
metaknowledge/contour/plotting.py
metaknowledge/genders/__init__.py
metaknowledge/genders/nameGender.py
metaknowledge/grants/__init__.py
metaknowledge/grants/baseGrant.py
metaknowledge/grants/cihrGrant.py
metaknowledge/grants/medlineGrant.py
metaknowledge/grants/nsercGrant.py
metaknowledge/grants/nsfGrant.py
metaknowledge/grants/scopusGrant.py
metaknowledge/journalAbbreviations/__init__.py
metaknowledge/journalAbbreviations/backend.py
metaknowledge/medline/__init__.py
metaknowledge/medline/medlineHandlers.py
metaknowledge/medline/recordMedline.py
metaknowledge/medline/tagProcessing/__init__.py
metaknowledge/medline/tagProcessing/specialFunctions.py
metaknowledge/medline/tagProcessing/tagFunctions.py
metaknowledge/medline/tagProcessing/tagNames.py
metaknowledge/proquest/__init__.py
metaknowledge/proquest/proQuestHandlers.py
metaknowledge/proquest/recordProQuest.py
metaknowledge/proquest/tagProcessing/__init__.py
metaknowledge/proquest/tagProcessing/specialFunctions.py
metaknowledge/proquest/tagProcessing/tagFunctions.py
metaknowledge/scopus/__init__.py
metaknowledge/scopus/recordScopus.py
metaknowledge/scopus/scopusHandlers.py
metaknowledge-3.4.1.dist-info/LICENSE
metaknowledge-3.4.1.dist-info/METADATA
metaknowledge-3.4.1.dist-info/WHEEL
metaknowledge-3.4.1.dist-info/entry_points.txt
metaknowledge-3.4.1.dist-info/top_level.txt
metaknowledge-3.4.1.dist-info/RECORD
