Metadata-Version: 2.1
Name: metaknowledge
Version: 3.4.1
Summary: A library for handling Web of science files
Home-page: https://github.com/networks-lab/metaknowledge
Author: Reid McIlroy-Young, John McLevey
Author-email: rmcilroy@uwaterloo.ca, john.mclevey@uwaterloo.ca
License: GPL
Download-URL: https://github.com/networks-lab/metaknowledge/archive/3.4.1.tar.gz
Keywords: WOS
Platform: UNKNOWN
Classifier: Development Status :: 5 - Production/Stable
Classifier: Environment :: Console
Classifier: Environment :: MacOS X
Classifier: Intended Audience :: Science/Research
Classifier: License :: OSI Approved :: GNU General Public License v2 (GPLv2)
Classifier: Operating System :: MacOS :: MacOS X
Classifier: Operating System :: POSIX
Classifier: Operating System :: Microsoft :: Windows
Classifier: Programming Language :: Python :: 3 :: Only
Classifier: Topic :: Education
Classifier: Topic :: Scientific/Engineering :: Information Analysis
Classifier: Topic :: Sociology
Classifier: Topic :: Text Processing
Provides-Extra: contour
